
COPYING.GPL
COPYING.TGPPL.html
README.txt
ez_setup.py
setup.py
dupfilefind/__init__.py
dupfilefind/_version.py
dupfilefind/cmdline_dupfilefind.py
dupfilefind/dff.py
dupfilefind/profiles.py
dupfilefind.egg-info/PKG-INFO
dupfilefind.egg-info/SOURCES.txt
dupfilefind.egg-info/dependency_links.txt
dupfilefind.egg-info/entry_points.txt
dupfilefind.egg-info/not-zip-safe
dupfilefind.egg-info/requires.txt
dupfilefind.egg-info/top_level.txt
setuptools_darcs-1.0.5-py2.5.egg/EGG-INFO/PKG-INFO
setuptools_darcs-1.0.5-py2.5.egg/EGG-INFO/SOURCES.txt
setuptools_darcs-1.0.5-py2.5.egg/EGG-INFO/dependency_links.txt
setuptools_darcs-1.0.5-py2.5.egg/EGG-INFO/entry_points.txt
setuptools_darcs-1.0.5-py2.5.egg/EGG-INFO/not-zip-safe
setuptools_darcs-1.0.5-py2.5.egg/EGG-INFO/top_level.txt
setuptools_darcs-1.0.5-py2.5.egg/setuptools_darcs/__init__.py
setuptools_darcs-1.0.5-py2.5.egg/setuptools_darcs/_version.py
setuptools_darcs-1.0.5-py2.5.egg/setuptools_darcs/setuptools_darcs.py